[{"id":1,"name":"Woy AI","url":"https://woy.ai","submission_url":"https://woy.ai/submit","dr":59,"monthly_traffic":43403,"pricing_type":"Free","founded_date":"unknown","created_at":"2024-07-07 09:17:53","updated_at":"2024-07-07 09:17:53","status":1},
{"id":2,"name":"Topai Tools","url":"https://topai.tools","submission_url":null,"dr":57,"monthly_traffic":1493257,"pricing_type":"Paid","founded_date":"2023-01-25 14:15:45","created_at":"2024-07-07 09:17:53","updated_at":"2024-07-07 09:17:53","status":0},
{"id":3,"name":"Tap4 AI","url":"https://tap4.ai","submission_url":"https://tap4.ai/submit","dr":52,"monthly_traffic":48869,"pricing_type":null,"founded_date":"unknown","created_at":"2024-07-07 09:17:53","updated_at":"2024-07-07 09:17:53","status":1},
{"id":4,"name":"AI Tool Net","url":"https://aitoolnet.com","submission_url":"https://www.aitoolnet.com/submit","dr":46,"monthly_traffic":61258,"pricing_type":null,"founded_date":"2023-03-01 06:47:33","created_at":"2024-07-07 09:17:53","updated_at":"2024-07-07 09:17:53","status":1},
{"id":5,"name":"AI Tool Center","url":"https://aitoolcenter.com","submission_url":"https://aitoolcenter.com/submit","dr":40,"monthly_traffic":18115,"pricing_type":null,"founded_date":"2024-05-17 23:19:18","created_at":"2024-07-07 09:17:53","updated_at":"2024-07-07 09:17:53","status":1},
{"id":6,"name":"Dokey AI","url":"https://dokeyai.com","submission_url":"https://dokeyai.com/submit","dr":40,"monthly_traffic":4598,"pricing_type":null,"founded_date":"2024-04-23 07:31:05","created_at":"2024-07-07 09:17:53","updated_at":"2024-07-07 09:17:53","status":0},
{"id":7,"name":"That AI Collection","url":"https://thataicollection.com","submission_url":null,"dr":37,"monthly_traffic":553397,"pricing_type":null,"founded_date":"2023-08-04 04:52:45","created_at":"2024-07-07 09:17:53","updated_at":"2024-07-07 09:17:53","status":0},
{"id":8,"name":"AI With Me","url":"https://aiwith.me","submission_url":"https://aiwith.me/submit","dr":37,"monthly_traffic":9090,"pricing_type":null,"founded_date":"2024-04-15 12:47:49","created_at":"2024-07-07 09:17:53","updated_at":"2024-07-07 09:17:53","status":1},
{"id":9,"name":"Whats AI Tools","url":"https://whatisaitools.com","submission_url":"https://whatisaitools.com/submit","dr":25,"monthly_traffic":24749,"pricing_type":null,"founded_date":"2024-03-29 08:12:05","created_at":"2024-07-07 09:17:53","updated_at":"2024-07-07 09:17:53","status":1},
{"id":10,"name":"IUU","url":"https://iuu.ai","submission_url":"https://iuu.ai/submit","dr":25,"monthly_traffic":6678,"pricing_type":null,"founded_date":"unknown","created_at":"2024-07-07 09:17:53","updated_at":"2024-07-07 09:17:53","status":1},
{"id":11,"name":"AI AI Tools","url":"https://aiai.tools","submission_url":"https://aiai.tools/submit","dr":24,"monthly_traffic":121,"pricing_type":null,"founded_date":"2024-04-15 09:21:00","created_at":"2024-07-07 09:17:53","updated_at":"2024-07-07 09:17:53","status":0},
{"id":12,"name":"TYY AI","url":"https://tyy.ai","submission_url":"https://tyy.ai/submit","dr":22,"monthly_traffic":36508,"pricing_type":null,"founded_date":"unknown","created_at":"2024-07-07 09:17:53","updated_at":"2024-07-07 09:17:53","status":0},
{"id":13,"name":"Fun Fun Tools","url":"https://funfun.tools","submission_url":"https://funfun.tools/submit","dr":21,"monthly_traffic":168765,"pricing_type":null,"founded_date":"2024-04-24 11:05:12","created_at":"2024-07-07 09:17:53","updated_at":"2024-07-07 09:17:53","status":0},
{"id":14,"name":"AI Monstr","url":"https://aimonstr.com","submission_url":"https://aimonstr.com/","dr":19,"monthly_traffic":32510,"pricing_type":null,"founded_date":"2024-05-20 07:51:45","created_at":"2024-07-07 09:17:53","updated_at":"2024-07-07 09:17:53","status":1},
{"id":15,"name":"AI Tool Hub","url":"https://aitoolhub.tech","submission_url":"https://aitoolhub.tech/submit","dr":18,"monthly_traffic":40526,"pricing_type":null,"founded_date":"2024-05-08 04:25:23","created_at":"2024-07-07 09:17:53","updated_at":"2024-07-07 09:17:53","status":0},
{"id":16,"name":"Bai Tools","url":"https://bai.tools","submission_url":"https://bai.tools/submit","dr":14,"monthly_traffic":36875,"pricing_type":null,"founded_date":"2023-12-02 04:08:28","created_at":"2024-07-07 09:17:53","updated_at":"2024-07-07 09:17:53","status":1},
{"id":17,"name":"Forit","url":"https://forit.ai","submission_url":"https://forit.ai/submit","dr":9,"monthly_traffic":15862,"pricing_type":null,"founded_date":"unknown","created_at":"2024-07-07 09:17:53","updated_at":"2024-07-07 09:17:53","status":0},
{"id":18,"name":"AI Nave","url":"https://ainave.com","submission_url":null,"dr":8,"monthly_traffic":7671,"pricing_type":null,"founded_date":"2023-05-05 19:51:27","created_at":"2024-07-07 09:17:53","updated_at":"2024-07-07 09:17:53","status":0},
{"id":19,"name":"Better AI Tools","url":"https://betteraitools.com","submission_url":"https://www.betteraitools.com/submit","dr":6,"monthly_traffic":17406,"pricing_type":null,"founded_date":"2024-05-25 07:28:56","created_at":"2024-07-07 09:17:53","updated_at":"2024-07-07 09:17:53","status":1},
{"id":20,"name":"AI Go Tools","url":"https://aigotools.com","submission_url":null,"dr":3.700000000000000177,"monthly_traffic":7747,"pricing_type":null,"founded_date":"2024-06-04 06:29:19","created_at":"2024-07-07 09:17:53","updated_at":"2024-07-07 09:17:53","status":1},
{"id":21,"name":"AI Navigation","url":"https://ai-navigation.net","submission_url":null,"dr":2.700000000000000177,"monthly_traffic":730,"pricing_type":null,"founded_date":"2024-05-07 14:21:02","created_at":"2024-07-07 09:17:53","updated_at":"2024-07-07 09:17:53","status":0},
{"id":22,"name":"YP For AI","url":"https://ypforai.com","submission_url":"https://ypforai.com/submit","dr":2,"monthly_traffic":8931,"pricing_type":null,"founded_date":"2024-06-12 18:55:39","created_at":"2024-07-07 09:17:53","updated_at":"2024-07-07 09:17:53","status":1},
{"id":23,"name":"Ask AI Tools","url":"https://askaitools.ai","submission_url":null,"dr":1.800000000000000044,"monthly_traffic":7647,"pricing_type":null,"founded_date":"unknown","created_at":"2024-07-07 09:17:53","updated_at":"2024-07-07 09:17:53","status":0},
{"id":24,"name":"Best AI Tool","url":"https://best-ai-tool.com","submission_url":"https://www.best-ai-tool.com/submit","dr":1.300000000000000044,"monthly_traffic":5457,"pricing_type":null,"founded_date":"2024-05-15 04:52:53","created_at":"2024-07-07 09:17:53","updated_at":"2024-07-07 09:17:53","status":1},
{"id":25,"name":"Your AI Tool","url":"https://youraitool.com/","submission_url":"https://youraitool.com/submit-tool","dr":29,"monthly_traffic":40259,"pricing_type":null,"founded_date":"2023-04-15 19:15:20","created_at":"2024-07-07 16:31:04","updated_at":"2024-07-07 16:31:04","status":0},
{"id":26,"name":"Navs Site","url":"https://navs.site/","submission_url":"https://navs.site/submit","dr":1,"monthly_traffic":0,"pricing_type":null,"founded_date":"2024-07-02 06:22:09","created_at":"2024-07-08 03:43:53","updated_at":"2024-07-08 03:43:53","status":1},
{"id":27,"name":"Dang AI","url":"https://dang.ai/","submission_url":"https://dang.ai/submit","dr":56,"monthly_traffic":165281,"pricing_type":null,"founded_date":"unknown","created_at":"2024-07-08 03:45:18","updated_at":"2024-07-08 03:45:18","status":0},
{"id":28,"name":"Dir2AI","url":"https://www.dir2ai.com/","submission_url":"https://www.dir2ai.com/user/dashboard","dr":14,"monthly_traffic":8013,"pricing_type":null,"founded_date":"2024-05-25 12:36:44","created_at":"2024-07-08 13:41:34","updated_at":"2024-07-08 13:41:34","status":1},
{"id":29,"name":"AITooly","url":"https://aitoolly.com/","submission_url":"https://aitoolly.com/submit","dr":1,"monthly_traffic":4775,"pricing_type":null,"founded_date":"2024-05-22 15:05:30","created_at":"2024-07-09 02:40:36","updated_at":"2024-07-09 02:40:36","status":1},
{"id":30,"name":"T0 AI","url":"https://t0ai.com/","submission_url":"https://t0ai.com/submit","dr":1,"monthly_traffic":0,"pricing_type":null,"founded_date":"2024-06-18 05:09:25","created_at":"2024-07-09 15:56:42","updated_at":"2024-07-09 15:56:42","status":1},
{"id":31,"name":"AIFnd","url":"https://aifnd.net/","submission_url":"https://aifnd.net/submit","dr":6,"monthly_traffic":17335,"pricing_type":null,"founded_date":"2024-05-08 08:48:35","created_at":"2024-07-10 02:42:25","updated_at":"2024-07-10 02:42:25","status":1},
{"id":32,"name":"SeekAIs","url":"https://seekais.com","submission_url":"https://seekais.com/submit","dr":1.600000000000000088,"monthly_traffic":0,"pricing_type":null,"founded_date":"2024-07-09 14:06:17","created_at":"2024-07-13 14:26:47","updated_at":"2024-07-13 14:26:47","status":1},
{"id":33,"name":"AI Tool Trek","url":"https://aitooltrek.com/","submission_url":"https://aitooltrek.com/submit","dr":1,"monthly_traffic":0,"pricing_type":null,"founded_date":"2024-07-17 04:48:22","created_at":"2024-07-19 07:01:25","updated_at":"2024-07-19 07:01:25","status":1},
{"id":34,"name":"FreeAITool","url":"https://freeaitool.ai/","submission_url":"https://freeaitool.ai/submit","dr":7,"monthly_traffic":0,"pricing_type":null,"founded_date":"unknown","created_at":"2024-09-15 04:03:25","updated_at":"2024-09-15 04:03:25","status":1},
{"id":35,"name":"Perchance AI","url":"https://perchance-ai.net/","submission_url":"https://perchance-ai.net/submit","dr":8,"monthly_traffic":null,"pricing_type":null,"founded_date":"2024-09-11 13:32:09","created_at":"2024-09-26 05:32:47","updated_at":"2024-09-26 05:32:47","status":0}]
